securecredentials/__init__.py
securecredentials/_version.py
securecredentials/core.py
securecredentials/exceptions.py
securecredentials/helper.py
securecredentials/schema_version.py
securecredentials/utils.py
securecredentials/.pytest_cache/.gitignore
securecredentials/.pytest_cache/CACHEDIR.TAG
securecredentials/.pytest_cache/README.md
securecredentials/.pytest_cache/v/cache/lastfailed
securecredentials/.pytest_cache/v/cache/nodeids
securecredentials/.pytest_cache/v/cache/stepwise
securecredentials-2.1.0.dist-info/METADATA
securecredentials-2.1.0.dist-info/WHEEL
securecredentials-2.1.0.dist-info/licenses/LICENSE
securecredentials-2.1.0.dist-info/RECORD
